openhasp_config_manager/__init__.py
openhasp_config_manager/cli/__init__.py
openhasp_config_manager/cli/cmd.py
openhasp_config_manager/cli/common.py
openhasp_config_manager/cli/deploy.py
openhasp_config_manager/cli/generate.py
openhasp_config_manager/cli/gui.py
openhasp_config_manager/cli/listen.py
openhasp_config_manager/cli/logs.py
openhasp_config_manager/cli/screenshot.py
openhasp_config_manager/cli/shell.py
openhasp_config_manager/cli/state.py
openhasp_config_manager/cli/upload.py
openhasp_config_manager/cli/vars.py
openhasp_config_manager/cli.py
openhasp_config_manager/const.py
openhasp_config_manager/manager.py
openhasp_config_manager/openhasp_client/__init__.py
openhasp_config_manager/openhasp_client/image_processor.py
openhasp_config_manager/openhasp_client/model/__init__.py
openhasp_config_manager/openhasp_client/model/component.py
openhasp_config_manager/openhasp_client/model/configuration/__init__.py
openhasp_config_manager/openhasp_client/model/configuration/config.py
openhasp_config_manager/openhasp_client/model/configuration/debug_config.py
openhasp_config_manager/openhasp_client/model/configuration/device_config.py
openhasp_config_manager/openhasp_client/model/configuration/gui_config.py
openhasp_config_manager/openhasp_client/model/configuration/hasp_config.py
openhasp_config_manager/openhasp_client/model/configuration/http_config.py
openhasp_config_manager/openhasp_client/model/configuration/mqtt_config.py
openhasp_config_manager/openhasp_client/model/configuration/screen_config.py
openhasp_config_manager/openhasp_client/model/configuration/telnet_config.py
openhasp_config_manager/openhasp_client/model/configuration/website_config.py
openhasp_config_manager/openhasp_client/model/configuration/wifi_config.py
openhasp_config_manager/openhasp_client/model/device.py
openhasp_config_manager/openhasp_client/model/openhasp_config_manager_config.py
openhasp_config_manager/openhasp_client/mqtt_client.py
openhasp_config_manager/openhasp_client/openhasp.py
openhasp_config_manager-0.7.0.dist-info/LICENSE
openhasp_config_manager-0.7.0.dist-info/METADATA
openhasp_config_manager-0.7.0.dist-info/WHEEL
openhasp_config_manager-0.7.0.dist-info/entry_points.txt
openhasp_config_manager-0.7.0.dist-info/RECORD
