Metadata-Version: 2.3
Name: openhasp-config-manager
Version: 0.7.0
Summary: A tool to manage all of your openHASP device configs in a centralized place.
License: AGPL-3.0-or-later
Keywords: openhasp,config,management
Author: Markus Ressel
Author-email: mail@markusressel.de
Requires-Python: >=3.12,<4.0
Classifier: Development Status :: 5 - Production/Stable
Classifier: License :: OSI Approved :: GNU Affero General Public License v3 or later (AGPLv3+)
Classifier: Programming Language :: Python :: 3
Classifier: Programming Language :: Python :: 3.12
Classifier: Programming Language :: Python :: 3.13
Classifier: Programming Language :: Python :: 3 :: Only
Classifier: Programming Language :: Python :: 3.10
Requires-Dist: Jinja2 (==3.1.6)
Requires-Dist: aiohttp (>=3.9.0,<3.12.0)
Requires-Dist: aiomqtt
Requires-Dist: click (==8.1.8)
Requires-Dist: frozenlist (==1.6.0)
Requires-Dist: multidict (==6.4.3)
Requires-Dist: orjson (==3.10.16)
Requires-Dist: paho-mqtt (>=1.6.1,<2.2.0)
Requires-Dist: pillow (==11.2.1)
Requires-Dist: py-range-parse (==1.0.5)
Requires-Dist: pyyaml (==6.0.2)
Requires-Dist: requests (==2.28.2)
Requires-Dist: telnetlib3 (==2.0.4)
Requires-Dist: temppathlib (==1.2.0)
Requires-Dist: yarl (==1.20.0)
Project-URL: Homepage, https://github.com/markusressel/openhasp-config-manager
Project-URL: Repository, https://github.com/markusressel/openhasp-config-manager
